CloudTrails_SDK-0.0.25.dist-info/DESCRIPTION.rst
CloudTrails_SDK-0.0.25.dist-info/METADATA
CloudTrails_SDK-0.0.25.dist-info/RECORD
CloudTrails_SDK-0.0.25.dist-info/WHEEL
CloudTrails_SDK-0.0.25.dist-info/metadata.json
CloudTrails_SDK-0.0.25.dist-info/top_level.txt
fc/__init__.py
fc/cloudtrailsdk/__init__.py
fc/cloudtrailsdk/execptions.py
fc/cloudtrailsdk/client/__init__.py
fc/cloudtrailsdk/client/tracker.py
fc/cloudtrailsdk/decorators/__init__.py
fc/cloudtrailsdk/decorators/custom_tracker.py
fc/cloudtrailsdk/decorators/exception_tracker.py
fc/cloudtrailsdk/middleware/__init__.py
fc/cloudtrailsdk/model/__init__.py
fc/cloudtrailsdk/model/event.py
fc/cloudtrailsdk/utils/__init__.py
fc/cloudtrailsdk/utils/functions.py
tests/__init__.py
tests/conftest.py
tests/test_tracker.py
